fst_lookup/__init__.py
fst_lookup/__version__.py
fst_lookup/_fst_lookup.c
fst_lookup/_fst_lookup.pyi
fst_lookup/data.py
fst_lookup/fallback_data.py
fst_lookup/flags.py
fst_lookup/fst.py
fst_lookup/parse.py
fst_lookup/symbol.py
fst_lookup/typedefs.py
fst_lookup-2024.7.3.dist-info/LICENSE
fst_lookup-2024.7.3.dist-info/METADATA
fst_lookup-2024.7.3.dist-info/WHEEL
fst_lookup-2024.7.3.dist-info/RECORD
