Metadata-Version: 2.1
Name: fst-lookup
Version: 2024.7.3
Summary: Lookup Foma FSTs
Home-page: https://github.com/eddieantonio/fst-lookup
License: MIT
Keywords: fst,lookup,transducer,morphology,foma
Author: Eddie Antonio Santos
Author-email: Eddie.Santos@nrc-cnrc.gc.ca
Requires-Python: >=3.8,<4.0
Classifier: Development Status :: 5 - Production/Stable
Classifier: License :: OSI Approved :: MIT License
Classifier: Programming Language :: Python :: 3
Classifier: Programming Language :: Python :: 3.8
Classifier: Programming Language :: Python :: 3.9
Classifier: Programming Language :: Python :: 3.10
Classifier: Programming Language :: Python :: 3.11
Classifier: Programming Language :: Python :: 3.12
Project-URL: Bug Tracker, https://github.com/eddieantonio/fst-lookup/issues
